squidasm/__init__.py
squidasm/nqasm/__init__.py
squidasm/nqasm/multithread.py
squidasm/nqasm/netstack.py
squidasm/nqasm/output.py
squidasm/nqasm/qnodeos.py
squidasm/nqasm/executor/__init__.py
squidasm/nqasm/executor/base.py
squidasm/nqasm/executor/nv.py
squidasm/nqasm/executor/vanilla.py
squidasm/nqasm/singlethread/__init__.py
squidasm/nqasm/singlethread/connection.py
squidasm/nqasm/singlethread/csocket.py
squidasm/run/__init__.py
squidasm/run/multithread/__init__.py
squidasm/run/multithread/runtime_mgr.py
squidasm/run/multithread/simulate.py
squidasm/run/singlethread/__init__.py
squidasm/run/singlethread/context.py
squidasm/run/singlethread/protocols.py
squidasm/run/singlethread/run.py
squidasm/run/singlethread/util.py
squidasm/run/stack/__init__.py
squidasm/run/stack/build.py
squidasm/run/stack/config.py
squidasm/run/stack/run.py
squidasm/sim/__init__.py
squidasm/sim/glob.py
squidasm/sim/queues.py
squidasm/sim/network/__init__.py
squidasm/sim/network/network.py
squidasm/sim/network/nv_config.py
squidasm/sim/stack/__init__.py
squidasm/sim/stack/common.py
squidasm/sim/stack/connection.py
squidasm/sim/stack/context.py
squidasm/sim/stack/csocket.py
squidasm/sim/stack/globals.py
squidasm/sim/stack/handler.py
squidasm/sim/stack/host.py
squidasm/sim/stack/netstack.py
squidasm/sim/stack/processor.py
squidasm/sim/stack/program.py
squidasm/sim/stack/qnos.py
squidasm/sim/stack/qnos_network_service.py
squidasm/sim/stack/signals.py
squidasm/sim/stack/stack.py
squidasm/sim/stack/arch/ARCH.md
squidasm/sim/stack/arch/arch.drawio
squidasm/sim/stack/arch/arch.png
squidasm/sim/stack/arch/comn.drawio
squidasm/sim/stack/arch/comn.png
squidasm/util/__init__.py
squidasm/util/ns.py
squidasm/util/qkd_routine.py
squidasm/util/routines.py
squidasm/util/sim.py
squidasm/util/thread.py
squidasm/util/util.py
squidasm-0.13.5.dist-info/licenses/LICENSE
squidasm-0.13.5.dist-info/METADATA
squidasm-0.13.5.dist-info/WHEEL
squidasm-0.13.5.dist-info/top_level.txt
squidasm-0.13.5.dist-info/RECORD
