Metadata-Version: 2.4
Name: squidasm
Version: 0.13.5
Summary: NetSquid simulator for quantum networks running NetQASM applications
Home-page: https://github.com/QuTech-Delft/squidasm
Author: QuTech
Author-email: b.vandervecht@tudelft.nl
License: MIT
License-File: LICENSE
Requires-Dist: netsquid-netbuilder<0.2.0,>=0.1.0
Requires-Dist: click<9.0,>=8.0
Requires-Dist: numpy<2.0,>=1.22
Requires-Dist: scipy<2.0,>=1.8
Requires-Dist: pydantic<3.0,>=1.8.2
Requires-Dist: pydynaa<2.0,>=0.3
Requires-Dist: netsquid<2.0,>=1.1.2
Requires-Dist: netsquid-magic<17.0.0,>=16.0.0
Requires-Dist: bitarray<3.0.0,>=2.8.0
Requires-Dist: netqasm>=0.11.2
Requires-Dist: pytest<8.0,>=7.1
Provides-Extra: dev
Requires-Dist: types-PyYAML<7.0,>=6.0; extra == "dev"
Requires-Dist: flake8<5.0,>=4.0; extra == "dev"
Requires-Dist: isort<5.11,>=5.10; extra == "dev"
Requires-Dist: black<22.4,>=22.3; extra == "dev"
Requires-Dist: mypy<0.951,>=0.950; extra == "dev"
Requires-Dist: pygments>=2.14; extra == "dev"
Provides-Extra: rtd
Requires-Dist: sphinx==6.1.3; extra == "rtd"
Requires-Dist: sphinx-rtd-theme==1.2.0; extra == "rtd"
Requires-Dist: sphinx-autodoc-typehints==1.22; extra == "rtd"
Dynamic: license-file
